minchin.pelican.jinja_filters-1.1.0-py3.9-nspkg.pth
minchin/pelican/jinja_filters/__init__.py
minchin.pelican.jinja_filters-1.1.0.dist-info/License.txt
minchin.pelican.jinja_filters-1.1.0.dist-info/METADATA
minchin.pelican.jinja_filters-1.1.0.dist-info/WHEEL
minchin.pelican.jinja_filters-1.1.0.dist-info/namespace_packages.txt
minchin.pelican.jinja_filters-1.1.0.dist-info/top_level.txt
minchin.pelican.jinja_filters-1.1.0.dist-info/RECORD
