Metadata-Version: 2.1
Name: minchin.pelican.jinja-filters
Version: 1.1.0
Summary: Jinja Filters for Pelican.
Home-page: https://github.com/MinchinWeb/minchin.pelican.jinja_filters
Author: William Minchin
Author-email: w_minchin@hotmail.com
License: MIT License
Platform: any
Classifier: Development Status :: 7 - Inactive
Classifier: Programming Language :: Python :: 3
Classifier: Programming Language :: Python :: 3.5
Classifier: Programming Language :: Python :: 3.6
Classifier: Programming Language :: Python :: 3.7
Classifier: Programming Language :: Python :: 3.8
Classifier: Programming Language :: Python :: 3.9
Classifier: Environment :: Web Environment
Classifier: Framework :: Pelican
Classifier: Intended Audience :: Developers
Classifier: Natural Language :: English
Classifier: Operating System :: OS Independent
Classifier: Topic :: Software Development :: Libraries :: Python Modules
Classifier: License :: OSI Approved :: MIT License
Requires-Dist: pelican
Requires-Dist: pelican-jinja-filters (>=2.1.0)
Provides-Extra: all
Requires-Dist: pip ; extra == 'all'
Requires-Dist: wheel ; extra == 'all'
Requires-Dist: setuptools (>=18.0) ; extra == 'all'
Requires-Dist: twine ; extra == 'all'
Requires-Dist: minchin.releaser (>=0.4.2) ; extra == 'all'
Provides-Extra: build
Requires-Dist: pip ; extra == 'build'
Requires-Dist: wheel ; extra == 'build'
Requires-Dist: setuptools (>=18.0) ; extra == 'build'
Requires-Dist: twine ; extra == 'build'
Requires-Dist: minchin.releaser (>=0.4.2) ; extra == 'build'
